{
  "main": {
    "id": "9f8d0b58376493ae",
    "type": "split",
    "children": [
      {
        "id": "04ed74520ff877d0",
        "type": "tabs",
        "children": [
          {
            "id": "20d68039df849775",
            "type": "leaf",
            "state": {
              "type": "markdown",
              "state": {
                "file": "08 Rust/99 练习.md",
                "mode": "source",
                "source": false
              }
            }
          }
        ]
      }
    ],
    "direction": "vertical"
  },
  "left": {
    "id": "a5f3857398a66dca",
    "type": "split",
    "children": [
      {
        "id": "9b081d1dcbb09b3d",
        "type": "tabs",
        "children": [
          {
            "id": "0784870a8a96b129",
            "type": "leaf",
            "state": {
              "type": "file-explorer",
              "state": {
                "sortOrder": "alphabetical"
              }
            }
          },
          {
            "id": "5a82046c28dd112d",
            "type": "leaf",
            "state": {
              "type": "search",
              "state": {
                "query": "",
                "matchingCase": false,
                "explainSearch": false,
                "collapseAll": false,
                "extraContext": false,
                "sortOrder": "alphabetical"
              }
            }
          },
          {
            "id": "555f3851a50ad3a9",
            "type": "leaf",
            "state": {
              "type": "starred",
              "state": {}
            }
          },
          {
            "id": "c1aceb2c40a59798",
            "type": "leaf",
            "state": {
              "type": "bookmarks",
              "state": {}
            }
          }
        ]
      }
    ],
    "direction": "horizontal",
    "width": 200
  },
  "right": {
    "id": "bdcab03c1ebed740",
    "type": "split",
    "children": [
      {
        "id": "3324d65b2d5a4ade",
        "type": "tabs",
        "children": [
          {
            "id": "aedb84c3cecd8cca",
            "type": "leaf",
            "state": {
              "type": "backlink",
              "state": {
                "file": "08 Rust/99 练习.md",
                "collapseAll": true,
                "extraContext": false,
                "sortOrder": "alphabetical",
                "showSearch": false,
                "searchQuery": "",
                "backlinkCollapsed": false,
                "unlinkedCollapsed": true
              }
            }
          },
          {
            "id": "2a38b67d0852181b",
            "type": "leaf",
            "state": {
              "type": "outgoing-link",
              "state": {
                "file": "08 Rust/99 练习.md",
                "linksCollapsed": false,
                "unlinkedCollapsed": true
              }
            }
          },
          {
            "id": "5f312cc2075dd1dd",
            "type": "leaf",
            "state": {
              "type": "tag",
              "state": {
                "sortOrder": "frequency",
                "useHierarchy": true
              }
            }
          },
          {
            "id": "c5f4ebd9f6cfbf03",
            "type": "leaf",
            "state": {
              "type": "outline",
              "state": {
                "file": "08 Rust/99 练习.md"
              }
            }
          },
          {
            "id": "0491ac81da3a241c",
            "type": "leaf",
            "state": {
              "type": "all-properties",
              "state": {
                "sortOrder": "frequency",
                "showSearch": false,
                "searchQuery": ""
              }
            }
          }
        ],
        "currentTab": 3
      }
    ],
    "direction": "horizontal",
    "width": 200
  },
  "left-ribbon": {
    "hiddenItems": {
      "canvas:新建白板": false,
      "switcher:打开快速切换": false,
      "graph:查看关系图谱": false,
      "daily-notes:打开/创建今天的日记": false,
      "templates:插入模板": false,
      "command-palette:打开命令面板": false
    }
  },
  "active": "20d68039df849775",
  "lastOpenFiles": [
    "08 Rust/88 实践.md",
    "08 Rust/99 练习.md",
    "05 Penetration Test/04 Web应用攻击.md",
    "07 More A&D/06 Web.md",
    "07 More A&D/05 Mobile.md",
    "08 Rust/06 包和模块.md",
    "08 Rust/08 错误处理.md",
    "08 Rust/07 常见集合.md",
    "08 Rust/04 结构体.md",
    "08 Rust/05 枚举.md",
    "08 Rust/03 所有权.md",
    "08 Rust/02 基础语法.md",
    "07 More A&D/03 Reverse.md",
    "07 More A&D/04 Crypto.md",
    "05 Penetration Test/09 传输后门.md",
    "05 Penetration Test/02 主动信息收集.md",
    "未命名.canvas",
    "02 Neovim/88 helix.md",
    "02 Neovim/07 自动补全.md",
    "02 Neovim/06 语言服务.md",
    "02 Neovim/05 语法分析.md",
    "02 Neovim/04 颜色主题.md",
    "02 Neovim/03 插件管理.md",
    "02 Neovim/02 键位映射.md",
    "02 Neovim/01 基础配置.md",
    "README.md",
    "06 practices/28 Funbox2.md",
    "0006.jpg",
    "assets/registers.png",
    "Pasted image 20231228104747.png",
    "Pasted image 20230519150816.png",
    "Pasted image 20230519150813.png",
    "08 Rust",
    "07 More A&D/未命名",
    "assets/screenshot.png"
  ]
}